{"lastUsed":1666681003434,"path":"C:\/Users\/user\/Desktop\/KIT","projectCount":1,"recentFiles":[{"path":"\/springJPA\/src\/test\/java\/namoo\/springJPA","parentWorkspace":"C:\/Users\/user\/Desktop\/KIT","name":"JpaRelationtwoway.java","lastModified":1666419499810,"locationURI":"file:\/C:\/Users\/user\/Desktop\/KIT\/springJPA\/src\/test\/java\/namoo\/springJPA\/JpaRelationtwoway.java"},{"path":"\/springJPA\/src\/test\/java\/namoo\/springJPA","parentWorkspace":"C:\/Users\/user\/Desktop\/KIT","name":"JpaRelationOneToOne.java","lastModified":1666421152920,"locationURI":"file:\/C:\/Users\/user\/Desktop\/KIT\/springJPA\/src\/test\/java\/namoo\/springJPA\/JpaRelationOneToOne.java"},{"path":"\/springJPA\/src\/test\/java\/namoo\/springJPA","parentWorkspace":"C:\/Users\/user\/Desktop\/KIT","name":"JpaRelationTest.java","lastModified":1666679532592,"locationURI":"file:\/C:\/Users\/user\/Desktop\/KIT\/springJPA\/src\/test\/java\/namoo\/springJPA\/JpaRelationTest.java"},{"path":"\/springJPA\/src\/main\/java\/namoo\/springJPA\/aop","parentWorkspace":"C:\/Users\/user\/Desktop\/KIT","name":"TimeTraceAspect.java","lastModified":1666681003435,"locationURI":"file:\/C:\/Users\/user\/Desktop\/KIT\/springJPA\/src\/main\/java\/namoo\/springJPA\/aop\/TimeTraceAspect.java"},{"path":"\/springJPA\/src\/test\/java\/namoo\/springJPA","parentWorkspace":"C:\/Users\/user\/Desktop\/KIT","name":"JPATEST.java","lastModified":1666417615159,"locationURI":"file:\/C:\/Users\/user\/Desktop\/KIT\/springJPA\/src\/test\/java\/namoo\/springJPA\/JPATEST.java"},{"path":"\/springJPA\/src\/main\/java\/namoo\/springJPA\/entity\/user","parentWorkspace":"C:\/Users\/user\/Desktop\/KIT","name":"Member.java","lastModified":1666420256023,"locationURI":"file:\/C:\/Users\/user\/Desktop\/KIT\/springJPA\/src\/main\/java\/namoo\/springJPA\/entity\/user\/Member.java"},{"path":"\/springJPA\/src\/main\/java\/namoo\/springJPA\/repository\/user","parentWorkspace":"C:\/Users\/user\/Desktop\/KIT","name":"jpaUserRepositoryDATA.java","lastModified":1666416208967,"locationURI":"file:\/C:\/Users\/user\/Desktop\/KIT\/springJPA\/src\/main\/java\/namoo\/springJPA\/repository\/user\/jpaUserRepositoryDATA.java"},{"path":"\/springJPA\/src\/main\/java\/namoo\/springJPA\/entity\/user","parentWorkspace":"C:\/Users\/user\/Desktop\/KIT","name":"Locker.java","lastModified":1666420733559,"locationURI":"file:\/C:\/Users\/user\/Desktop\/KIT\/springJPA\/src\/main\/java\/namoo\/springJPA\/entity\/user\/Locker.java"},{"path":"\/springJPA\/src\/main\/java\/namoo\/springJPA\/repository\/user","parentWorkspace":"C:\/Users\/user\/Desktop\/KIT","name":"JpaLockerRepository.java","lastModified":1666420400055,"locationURI":"file:\/C:\/Users\/user\/Desktop\/KIT\/springJPA\/src\/main\/java\/namoo\/springJPA\/repository\/user\/JpaLockerRepository.java"},{"path":"\/springJPA\/src\/main\/java\/namoo\/springJPA\/Service","parentWorkspace":"C:\/Users\/user\/Desktop\/KIT","name":"MemberService.java","lastModified":1666680846105,"locationURI":"file:\/C:\/Users\/user\/Desktop\/KIT\/springJPA\/src\/main\/java\/namoo\/springJPA\/Service\/MemberService.java"},{"path":"\/springJPA\/src\/test\/java\/namoo\/springJPA","parentWorkspace":"C:\/Users\/user\/Desktop\/KIT","name":"SpringAOP.java","lastModified":1666680899835,"locationURI":"file:\/C:\/Users\/user\/Desktop\/KIT\/springJPA\/src\/test\/java\/namoo\/springJPA\/SpringAOP.java"}]}